adam/__init__.py
adam/app.py
adam/assembly.py
adam/build.py
adam/code.py
adam/error.py
adam/file.py
adam/grammar.py
adam/help.py
adam/lex.py
adam/run.py
adam/syntax.py
adam/token.py
adam/translation.py
adam/types.py
adam/utils.py
adam/zones.py
adam/embedding/__init__.py
adam/embedding/nqs.py
adam/embedding/python.py
adam/semantic/__init__.py
adam/semantic/python.py
adam/templates/__init__.py
adam/templates/english.py
adam/templates/french.py
adam/templates/spanish.py
nqs/__init__.py
nqs/core/__init__.py
nqs/core/functions.py
nqs/core/kernel.py
nqs/core/quantum.py
nqs/core/reader.py
nqs/developer/__init__.py
nqs/developer/app.py
nqs/developer/run.py
nqs/developer/write.py
user/__init__.py
user/definitions.py
user/index.py
user/private.py
nateve_adam-0.0.3.dist-info/LICENSE
nateve_adam-0.0.3.dist-info/METADATA
nateve_adam-0.0.3.dist-info/WHEEL
nateve_adam-0.0.3.dist-info/entry_points.txt
nateve_adam-0.0.3.dist-info/top_level.txt
nateve_adam-0.0.3.dist-info/RECORD
