Metadata-Version: 2.1
Name: nateve-adam
Version: 0.0.3
Summary: Nateve transpiler developed with python 3.8
Home-page: https://github.com/NateveLang/Adam
Author: Emmanuel Norambuena
Author-email: eanorambuena@uc.cl
License: MIT
Download-URL: https://github.com/NateveLang/Adam/archive/v0.0.3.tar.gz
Project-URL: Bug Reports, https://github.com/NateveLang/Adam/issues
Project-URL: Source, https://github.com/NateveLang/Adam
Keywords: development,quantum computing,programming language,nateve,natevelang,nate,education
Platform: UNKNOWN
Classifier: Development Status :: 5 - Production/Stable
Classifier: Intended Audience :: Developers
Classifier: Topic :: Software Development :: Build Tools
Classifier: License :: OSI Approved :: MIT License
Classifier: Programming Language :: Python :: 3.5
Classifier: Programming Language :: Python :: 3.6
Classifier: Programming Language :: Python :: 3.7
Classifier: Programming Language :: Python :: 3.8
Requires-Python: >=3.5, <=3.8
License-File: LICENSE
Requires-Dist: eggdriver
Requires-Dist: qiskit
